README.md
setup.py
genius_lite/__init__.py
genius_lite.egg-info/PKG-INFO
genius_lite.egg-info/SOURCES.txt
genius_lite.egg-info/dependency_links.txt
genius_lite.egg-info/requires.txt
genius_lite.egg-info/top_level.txt
genius_lite/core/__init__.py
genius_lite/core/genius_lite.py
genius_lite/http/__init__.py
genius_lite/http/record.py
genius_lite/http/request.py
genius_lite/http/user_agent.py
genius_lite/log/__init__.py
genius_lite/log/colored_formatter.py
genius_lite/log/escape_codes.py
genius_lite/log/logger.py
genius_lite/seed/__init__.py
genius_lite/seed/seed.py
genius_lite/seed/store.py
genius_lite/utils/__init__.py
genius_lite/utils/tool.py
tests/__init__.py
tests/test.py