Metadata-Version: 2.1
Name: genius-lite
Version: 0.2.5
Summary: A Light Spider(Web Crawler) System in Python
Home-page: https://github.com/f840415070/genius-lite
Author: fanyibin
Author-email: f84041507@163.com
License: MIT Licence
Keywords: Spider,Web Crawler,requests
Platform: any
